core_eda/__init__.py
core_eda/distribution_check.py
core_eda/eda_table.py
core_eda/eda_text.py
core_eda/functions.py
core_eda/machine_learning.py
core_eda/visualization.py
core_eda-0.0.32.dist-info/METADATA
core_eda-0.0.32.dist-info/WHEEL
core_eda-0.0.32.dist-info/licenses/LICENSE
core_eda-0.0.32.dist-info/RECORD
