Metadata-Version: 2.4
Name: core_eda
Version: 0.0.32
Summary: A name matching package
Project-URL: Homepage, https://github.com/kevinkhang2909/core_eda
Project-URL: Bug Tracker, https://github.com/kevinkhang2909/core_eda/issues
Author-email: Kevin Khang <kevinkhang2909@gmail.com>
License: Copyright (c) 2024 Kevin Khang
License-File: LICENSE
Keywords: data science,eda
Classifier: License :: OSI Approved :: MIT License
Classifier: Operating System :: OS Independent
Classifier: Programming Language :: Python :: 3
Requires-Python: >=3.11
Requires-Dist: duckdb
Requires-Dist: emoji
Requires-Dist: holidays
Requires-Dist: matplotlib
Requires-Dist: scikit-learn
Requires-Dist: seaborn
Requires-Dist: tqdm
Requires-Dist: xgboost
